uart_rx.v
module uart_rx (
    input clk,
    input reset,
    input rx,
    input tick,
    output reg [7:0] rx_data,
    output reg rx_done
);

    parameter IDLE = 3'b000;
    parameter START = 3'b001;
    parameter DATA = 3'b010;
    parameter STOP = 3'b011;
    parameter DONE = 3'b100;

    reg [2:0] state;
    reg [2:0] bit_index;

    always @(posedge clk or posedge reset) begin
        if(reset) begin
            state <= IDLE;
            rx_data <= 0;
            rx_done <= 0;
            bit_index <= 0;
        end else begin 
            case (state)

                IDLE: begin
                    rx_done <= 0;
                    if(rx == 0)  //start bit detected
                        state <= START;
                end

                START: begin
                    if (tick) begin
                        if (rx == 0) begin   // confirm start bit
                            state <= DATA;
                            bit_index <= 0;
                        end else begin
                            state <= IDLE;   // false start
                        end
                    end
                end

                DATA: begin
                    if (tick) begin
                        rx_data[bit_index] <= rx;
                        if(bit_index == 7)
                            state <= STOP;
                        else 
                            bit_index <= bit_index + 1;
                    end
                end

                STOP: begin
                    if (tick) begin
                        state <= DONE;
                    end
                end

                DONE: begin
                    rx_done <= 1;
                    state <= IDLE;
                end

            endcase
        end
    end

endmodule

uart_tx.v
module uart_tx (
    input clk,
    input reset,
    input tx_start,
    input tick,
    input [7:0] tx_data,
    output reg tx,
    output reg tx_busy
);

    // FSM states
    parameter IDLE  = 2'b00;
    parameter START = 2'b01;
    parameter DATA  = 2'b10;
    parameter STOP  = 2'b11;

    reg [1:0] state;
    reg [7:0] data_reg;
    reg [2:0] bit_index;

    always @(posedge clk or posedge reset) begin
        if (reset) begin
            state <= IDLE;
            tx <= 1;
            tx_busy <= 0;
            bit_index <= 0;
        end else begin
            case (state)

                IDLE: begin
                    tx <= 1;
                    tx_busy <= 0;
                    if (tx_start) begin
                        data_reg <= tx_data;
                        state <= START;
                        tx_busy <= 1;
                    end
                end

                START: begin
                    if (tick) begin
                        tx <= 0; // start bit
                        state <= DATA;
                        bit_index <= 0;
                    end
                end

                DATA: begin
                    if (tick) begin
                        tx <= data_reg[bit_index];
                        if (bit_index == 7)
                            state <= STOP;
                        else
                            bit_index <= bit_index + 1;
                    end
                end

                STOP: begin
                    if (tick) begin
                        tx <= 1; // stop bit
                        state <= IDLE;
                    end
                end

            endcase
        end
    end

endmodule

baud_gen.v
module baud_gen #(
    parameter CLK_FREQ = 50000000,   // 50 MHz
    parameter BAUD_RATE = 9600
)(
    input clk,
    input reset,
    output reg tick
);

    localparam DIVISOR = 10;   // TEMP FOR SIMULATION
    reg [15:0] counter;

    always @(posedge clk or posedge reset) begin
        if (reset) begin
            counter <= 0;
            tick <= 0;
        end else begin
            if (counter == DIVISOR - 1) begin
                counter <= 0;
                tick <= 1;  // pulse
            end else begin
                counter <= counter + 1;
                tick <= 0;
            end
        end
    end

endmodule

uart_tb.v
`timescale 1ns/1ps

module uart_tb;

    reg clk;
    reg reset;
    reg tx_start;
    reg [7:0] tx_data;

    wire tx;
    wire tx_busy;
    wire tick;

    wire rx;
    assign rx = tx;

    wire [7:0] rx_data;
    wire rx_done;

    baud_gen bg (
        .clk(clk),
        .reset(reset),
        .tick(tick)
    );

    // Instantiate UART TX
    uart_tx uut (
        .clk(clk),
        .reset(reset),
        .tx_start(tx_start),
        .tx_data(tx_data),
        .tick(tick),
        .tx(tx),
        .tx_busy(tx_busy)
    );

    //Instantiate UART rx
    uart_rx rx_unit (
        .clk(clk),
        .reset(reset),
        .rx(rx),
        .tick(tick),
        .rx_data(rx_data),
        .rx_done(rx_done)
    );

    // Clock generation (10ns period)
    always #5 clk = ~clk;

    initial begin
        // Initialize
        clk = 0;
        reset = 1;
        tx_start = 0;
        tx_data = 8'b10101100;

        // Reset pulse
        #10 reset = 0;

        // Start transmission
        #10 tx_start = 1;
        #10 tx_start = 0;

        // Wait for the receiver to finish and check the received byte.
        @(posedge rx_done);
        #1;
        if (rx_data == tx_data)
            $display("PASS: rx_data = %b, tx_data = %b", rx_data, tx_data);
        else
            $display("FAIL: rx_data = %b, tx_data = %b", rx_data, tx_data);

        // Small delay so the result is visible before ending simulation.
        #20;

        $finish;
    end

    // Dump waveform
    initial begin
        $dumpfile("wave.vcd");
        $dumpvars(0, uart_tb);
    end

endmodule

wave.vcd
$date
	Wed Mar 18 15:45:07 2026
$end
$version
	Icarus Verilog
$end
$timescale
	1ps
$end
$scope module uart_tb $end
$var wire 1 ! rx $end
$var wire 1 " tx_busy $end
$var wire 1 # tx $end
$var wire 1 $ tick $end
$var wire 1 % rx_done $end
$var wire 8 & rx_data [7:0] $end
$var reg 1 ' clk $end
$var reg 1 ( reset $end
$var reg 8 ) tx_data [7:0] $end
$var reg 1 * tx_start $end
$scope module bg $end
$var wire 1 ' clk $end
$var wire 1 ( reset $end
$var parameter 32 + BAUD_RATE $end
$var parameter 32 , CLK_FREQ $end
$var parameter 32 - DIVISOR $end
$var reg 16 . counter [15:0] $end
$var reg 1 $ tick $end
$upscope $end
$scope module rx_unit $end
$var wire 1 ' clk $end
$var wire 1 ( reset $end
$var wire 1 ! rx $end
$var wire 1 $ tick $end
$var parameter 3 / DATA $end
$var parameter 3 0 DONE $end
$var parameter 3 1 IDLE $end
$var parameter 3 2 START $end
$var parameter 3 3 STOP $end
$var reg 3 4 bit_index [2:0] $end
$var reg 8 5 rx_data [7:0] $end
$var reg 1 % rx_done $end
$var reg 3 6 state [2:0] $end
$upscope $end
$scope module uut $end
$var wire 1 ' clk $end
$var wire 1 ( reset $end
$var wire 1 $ tick $end
$var wire 8 7 tx_data [7:0] $end
$var wire 1 * tx_start $end
$var parameter 2 8 DATA $end
$var parameter 2 9 IDLE $end
$var parameter 2 : START $end
$var parameter 2 ; STOP $end
$var reg 3 < bit_index [2:0] $end
$var reg 8 = data_reg [7:0] $end
$var reg 2 > state [1:0] $end
$var reg 1 # tx $end
$var reg 1 " tx_busy $end
$upscope $end
$upscope $end
$enddefinitions $end
$comment Show the parameter values. $end
$dumpall
b11 ;
b1 :
b0 9
b10 8
b11 3
b1 2
b0 1
b100 0
b10 /
b1010 -
b10111110101111000010000000 ,
b10010110000000 +
$end
#0
$dumpvars
b0 >
bx =
b0 <
b10101100 7
b0 6
b0 5
b0 4
b0 .
0*
b10101100 )
1(
0'
b0 &
0%
0$
1#
0"
1!
$end
#5000
1'
#10000
0'
0(
#15000
b1 .
1'
#20000
0'
1*
#25000
1"
b1 >
b10101100 =
b10 .
1'
#30000
0'
0*
#35000
b11 .
1'
#40000
0'
#45000
b100 .
1'
#50000
0'
#55000
b101 .
1'
#60000
0'
#65000
b110 .
1'
#70000
0'
#75000
b111 .
1'
#80000
0'
#85000
b1000 .
1'
#90000
0'
#95000
b1001 .
1'
#100000
0'
#105000
1$
b0 .
1'
#110000
0'
#115000
0$
b1 .
b10 >
0!
0#
1'
#120000
0'
#125000
b1 6
b10 .
1'
#130000
0'
#135000
b11 .
1'
#140000
0'
#145000
b100 .
1'
#150000
0'
#155000
b101 .
1'
#160000
0'
#165000
b110 .
1'
#170000
0'
#175000
b111 .
1'
#180000
0'
#185000
b1000 .
1'
#190000
0'
#195000
b1001 .
1'
#200000
0'
#205000
1$
b0 .
1'
#210000
0'
#215000
0$
b1 .
b1 <
b10 6
1'
#220000
0'
#225000
b10 .
1'
#230000
0'
#235000
b11 .
1'
#240000
0'
#245000
b100 .
1'
#250000
0'
#255000
b101 .
1'
#260000
0'
#265000
b110 .
1'
#270000
0'
#275000
b111 .
1'
#280000
0'
#285000
b1000 .
1'
#290000
0'
#295000
b1001 .
1'
#300000
0'
#305000
1$
b0 .
1'
#310000
0'
#315000
0$
b1 .
b10 <
b1 4
1'
#320000
0'
#325000
b10 .
1'
#330000
0'
#335000
b11 .
1'
#340000
0'
#345000
b100 .
1'
#350000
0'
#355000
b101 .
1'
#360000
0'
#365000
b110 .
1'
#370000
0'
#375000
b111 .
1'
#380000
0'
#385000
b1000 .
1'
#390000
0'
#395000
b1001 .
1'
#400000
0'
#405000
1$
b0 .
1'
#410000
0'
#415000
0$
b1 .
b11 <
1!
1#
b10 4
1'
#420000
0'
#425000
b10 .
1'
#430000
0'
#435000
b11 .
1'
#440000
0'
#445000
b100 .
1'
#450000
0'
#455000
b101 .
1'
#460000
0'
#465000
b110 .
1'
#470000
0'
#475000
b111 .
1'
#480000
0'
#485000
b1000 .
1'
#490000
0'
#495000
b1001 .
1'
#500000
0'
#505000
1$
b0 .
1'
#510000
0'
#515000
0$
b1 .
b100 <
b11 4
b100 &
b100 5
1'
#520000
0'
#525000
b10 .
1'
#530000
0'
#535000
b11 .
1'
#540000
0'
#545000
b100 .
1'
#550000
0'
#555000
b101 .
1'
#560000
0'
#565000
b110 .
1'
#570000
0'
#575000
b111 .
1'
#580000
0'
#585000
b1000 .
1'
#590000
0'
#595000
b1001 .
1'
#600000
0'
#605000
1$
b0 .
1'
#610000
0'
#615000
0$
b1 .
b101 <
0!
0#
b100 4
b1100 &
b1100 5
1'
#620000
0'
#625000
b10 .
1'
#630000
0'
#635000
b11 .
1'
#640000
0'
#645000
b100 .
1'
#650000
0'
#655000
b101 .
1'
#660000
0'
#665000
b110 .
1'
#670000
0'
#675000
b111 .
1'
#680000
0'
#685000
b1000 .
1'
#690000
0'
#695000
b1001 .
1'
#700000
0'
#705000
1$
b0 .
1'
#710000
0'
#715000
0$
b1 .
b110 <
1!
1#
b101 4
1'
#720000
0'
#725000
b10 .
1'
#730000
0'
#735000
b11 .
1'
#740000
0'
#745000
b100 .
1'
#750000
0'
#755000
b101 .
1'
#760000
0'
#765000
b110 .
1'
#770000
0'
#775000
b111 .
1'
#780000
0'
#785000
b1000 .
1'
#790000
0'
#795000
b1001 .
1'
#800000
0'
#805000
1$
b0 .
1'
#810000
0'
#815000
0$
b1 .
b111 <
0!
0#
b110 4
b101100 &
b101100 5
1'
#820000
0'
#825000
b10 .
1'
#830000
0'
#835000
b11 .
1'
#840000
0'
#845000
b100 .
1'
#850000
0'
#855000
b101 .
1'
#860000
0'
#865000
b110 .
1'
#870000
0'
#875000
b111 .
1'
#880000
0'
#885000
b1000 .
1'
#890000
0'
#895000
b1001 .
1'
#900000
0'
#905000
1$
b0 .
1'
#910000
0'
#915000
0$
b1 .
b11 >
1!
1#
b111 4
1'
#920000
0'
#925000
b10 .
1'
#930000
0'
#935000
b11 .
1'
#940000
0'
#945000
b100 .
1'
#950000
0'
#955000
b101 .
1'
#960000
0'
#965000
b110 .
1'
#970000
0'
#975000
b111 .
1'
#980000
0'
#985000
b1000 .
1'
#990000
0'
#995000
b1001 .
1'
#1000000
0'
#1005000
1$
b0 .
1'
#1010000
0'
#1015000
0$
b1 .
b0 >
b11 6
b10101100 &
b10101100 5
1'
#1020000
0'
#1025000
0"
b10 .
1'
#1030000
0'
#1035000
b11 .
1'
#1040000
0'
#1045000
b100 .
1'
#1050000
0'
#1055000
b101 .
1'
#1060000
0'
#1065000
b110 .
1'
#1070000
0'
#1075000
b111 .
1'
#1080000
0'
#1085000
b1000 .
1'
#1090000
0'
#1095000
b1001 .
1'
#1100000
0'
#1105000
1$
b0 .
1'
#1110000
0'
#1115000
0$
b1 .
b100 6
1'
#1120000
0'
#1125000
b0 6
1%
b10 .
1'
#1130000
0'
#1135000
b11 .
0%
1'
#1140000
0'
#1145000
b100 .
1'
